{"ConfigDataVersion":"1.0.0.8","Description":"hello","Integrations":[{"IsNormalizationEnabled":false,"QueuePathPrefix":null,"InvolvedWaitingRoomIds":null,"VerifyQueueIdEnabled":null,"QueueIdUsageLimit":null,"IsCookieHttpOnly":null,"IsCookieSecure":null,"Name":"Good Bots - Akamai","ActionType":"Ignore","EventId":null,"CookieDomain":null,"LayoutName":null,"Culture":null,"ExtendCookieValidity":null,"CookieValidityMinute":0,"Triggers":[{"TriggerParts":[{"Operator":"Contains","ValueToCompare":"bot","ValuesToCompare":null,"UrlPart":null,"CookieName":null,"HttpHeaderName":"Akamai-bot","ValidatorType":"HttpHeaderValidator","IsNegative":false,"IsIgnoreCase":true}],"LogicalOperator":"And"}],"QueueDomain":null,"RedirectLogic":null,"ForcedTargetUrl":null},{"IsNormalizationEnabled":false,"QueuePathPrefix":null,"InvolvedWaitingRoomIds":null,"VerifyQueueIdEnabled":null,"QueueIdUsageLimit":null,"IsCookieHttpOnly":null,"IsCookieSecure":null,"Name":"Ignore Good Bot","ActionType":"Ignore","EventId":null,"CookieDomain":null,"LayoutName":null,"Culture":null,"ExtendCookieValidity":null,"CookieValidityMinute":0,"Triggers":[{"TriggerParts":[{"Operator":"ContainsAny","ValueToCompare":"","ValuesToCompare":["adsbot-google","AdsBot-Google-Mobile","AdsBot-Google-Mobile-Apps","AhrefsBot","APIs-Google","Applebot","Baiduspider","bingbot","BingPreview","DotBot","DuckDuckBot","DuplexWeb-Google","facebookexternalhit","Facebot","FeedFetcher-Google","Google Favicon","Google-Adwords-Instant","Google-Read-Aloud","Google-Site-Verification","googlebot","Googlebot-image","Googlebot-News","Googlebot-Video","Image size by Siteimprove.com","LinkCheck by Siteimprove.com","Mail.RU_Bot","Mappy","Mediapartners-Google","MJ12bot","nlnbot","Pinterestbot","Prerender","SemrushBot","SiteCheck-sitecrawl by Siteimprove.com","Slackbot-LinkExpanding","UptimeRobot","Yahoo! Slurp","Yahoo!-AdCrawler","YandexBot","GoogleBots","Google-InspectionTool"],"UrlPart":null,"CookieName":null,"HttpHeaderName":null,"ValidatorType":"UserAgentValidator","IsNegative":false,"IsIgnoreCase":true}],"LogicalOperator":"And"}],"QueueDomain":null,"RedirectLogic":null,"ForcedTargetUrl":null},{"IsNormalizationEnabled":false,"QueuePathPrefix":null,"InvolvedWaitingRoomIds":null,"VerifyQueueIdEnabled":null,"QueueIdUsageLimit":null,"IsCookieHttpOnly":null,"IsCookieSecure":null,"Name":"Testing for Korean air","ActionType":"Ignore","EventId":null,"CookieDomain":null,"LayoutName":null,"Culture":null,"ExtendCookieValidity":null,"CookieValidityMinute":0,"Triggers":[{"TriggerParts":[{"Operator":"Contains","ValueToCompare":"https://sale-test-ecommerce.queue-it-demo.com","ValuesToCompare":null,"UrlPart":"PageUrl","CookieName":null,"HttpHeaderName":null,"ValidatorType":"UrlValidator","IsNegative":false,"IsIgnoreCase":true}],"LogicalOperator":"And"}],"QueueDomain":null,"RedirectLogic":null,"ForcedTargetUrl":null},{"IsNormalizationEnabled":false,"QueuePathPrefix":"","InvolvedWaitingRoomIds":null,"VerifyQueueIdEnabled":null,"QueueIdUsageLimit":null,"IsCookieHttpOnly":false,"IsCookieSecure":false,"Name":"EastarJet Testing 1","ActionType":"Queue","EventId":"ecommerce","CookieDomain":"","LayoutName":null,"Culture":null,"ExtendCookieValidity":true,"CookieValidityMinute":20,"Triggers":[{"TriggerParts":[{"Operator":"Contains","ValueToCompare":"https://sale-test-ecommerce.queue-it-demo.com/index.html","ValuesToCompare":null,"UrlPart":"PageUrl","CookieName":null,"HttpHeaderName":null,"ValidatorType":"UrlValidator","IsNegative":false,"IsIgnoreCase":true}],"LogicalOperator":"And"}],"QueueDomain":"saletest.queue-it.net","RedirectLogic":"AllowTParameter","ForcedTargetUrl":null},{"IsNormalizationEnabled":false,"QueuePathPrefix":"","InvolvedWaitingRoomIds":null,"VerifyQueueIdEnabled":null,"QueueIdUsageLimit":null,"IsCookieHttpOnly":false,"IsCookieSecure":false,"Name":"EastarJet Testing2","ActionType":"Queue","EventId":"knownuser","CookieDomain":"","LayoutName":null,"Culture":null,"ExtendCookieValidity":true,"CookieValidityMinute":20,"Triggers":[{"TriggerParts":[{"Operator":"Contains","ValueToCompare":"https://sale-test-ecommerce.queue-it-demo.com/queueit.html","ValuesToCompare":null,"UrlPart":"PageUrl","CookieName":null,"HttpHeaderName":null,"ValidatorType":"UrlValidator","IsNegative":false,"IsIgnoreCase":true}],"LogicalOperator":"And"}],"QueueDomain":"saletest.queue-it.net","RedirectLogic":"AllowTParameter","ForcedTargetUrl":null},{"IsNormalizationEnabled":false,"QueuePathPrefix":"","InvolvedWaitingRoomIds":null,"VerifyQueueIdEnabled":null,"QueueIdUsageLimit":null,"IsCookieHttpOnly":false,"IsCookieSecure":false,"Name":"Copy of EastarJet Testing2","ActionType":"Queue","EventId":"knownuser","CookieDomain":"","LayoutName":null,"Culture":null,"ExtendCookieValidity":true,"CookieValidityMinute":20,"Triggers":[{"TriggerParts":[{"Operator":"Contains","ValueToCompare":"sale-test-ecommerce.queue-it-demo.com/shipping.html","ValuesToCompare":null,"UrlPart":"PageUrl","CookieName":null,"HttpHeaderName":null,"ValidatorType":"UrlValidator","IsNegative":false,"IsIgnoreCase":true}],"LogicalOperator":"And"}],"QueueDomain":"saletest.queue-it.net","RedirectLogic":"AllowTParameter","ForcedTargetUrl":null},{"IsNormalizationEnabled":false,"QueuePathPrefix":"","InvolvedWaitingRoomIds":null,"VerifyQueueIdEnabled":null,"QueueIdUsageLimit":null,"IsCookieHttpOnly":false,"IsCookieSecure":false,"Name":"Copy of EastarJet Testing2 (3)","ActionType":"Queue","EventId":"knownuser","CookieDomain":"","LayoutName":null,"Culture":null,"ExtendCookieValidity":true,"CookieValidityMinute":20,"Triggers":[{"TriggerParts":[{"Operator":"Contains","ValueToCompare":"sale-test-ecommerce.queue-it-demo.com/ai.html","ValuesToCompare":null,"UrlPart":"PageUrl","CookieName":null,"HttpHeaderName":null,"ValidatorType":"UrlValidator","IsNegative":false,"IsIgnoreCase":true}],"LogicalOperator":"And"}],"QueueDomain":"saletest.queue-it.net","RedirectLogic":"AllowTParameter","ForcedTargetUrl":null},{"IsNormalizationEnabled":false,"QueuePathPrefix":"","InvolvedWaitingRoomIds":null,"VerifyQueueIdEnabled":null,"QueueIdUsageLimit":null,"IsCookieHttpOnly":false,"IsCookieSecure":false,"Name":"Copy of EastarJet Testing2 (2)","ActionType":"Queue","EventId":"knownuser","CookieDomain":"","LayoutName":null,"Culture":null,"ExtendCookieValidity":true,"CookieValidityMinute":20,"Triggers":[{"TriggerParts":[{"Operator":"Contains","ValueToCompare":"sale-test-ecommerce.queue-it-demo.com/healthcare.html","ValuesToCompare":null,"UrlPart":"PageUrl","CookieName":null,"HttpHeaderName":null,"ValidatorType":"UrlValidator","IsNegative":false,"IsIgnoreCase":true}],"LogicalOperator":"And"}],"QueueDomain":"saletest.queue-it.net","RedirectLogic":"AllowTParameter","ForcedTargetUrl":null},{"IsNormalizationEnabled":false,"QueuePathPrefix":"","InvolvedWaitingRoomIds":null,"VerifyQueueIdEnabled":null,"QueueIdUsageLimit":null,"IsCookieHttpOnly":false,"IsCookieSecure":false,"Name":"Ecommerce Italian","ActionType":"Queue","EventId":"aiwaitingroom","CookieDomain":"","LayoutName":null,"Culture":"it-IT","ExtendCookieValidity":true,"CookieValidityMinute":20,"Triggers":[{"TriggerParts":[{"Operator":"Equals","ValueToCompare":"https://sale-test-ecommerce.queue-it-demo.com/","ValuesToCompare":null,"UrlPart":"PageUrl","CookieName":null,"HttpHeaderName":null,"ValidatorType":"UrlValidator","IsNegative":false,"IsIgnoreCase":true},{"Operator":"Contains","ValueToCompare":"it","ValuesToCompare":null,"UrlPart":null,"CookieName":"slang","HttpHeaderName":null,"ValidatorType":"CookieValidator","IsNegative":false,"IsIgnoreCase":true}],"LogicalOperator":"And"}],"QueueDomain":"saletest.queue-it.net","RedirectLogic":"AllowTParameter","ForcedTargetUrl":null},{"IsNormalizationEnabled":false,"QueuePathPrefix":"","InvolvedWaitingRoomIds":["ecommerce"],"VerifyQueueIdEnabled":null,"QueueIdUsageLimit":null,"IsCookieHttpOnly":false,"IsCookieSecure":false,"Name":"EastarJet Testing 3","ActionType":"Cancel","EventId":"ecommerce","CookieDomain":"","LayoutName":null,"Culture":null,"ExtendCookieValidity":null,"CookieValidityMinute":0,"Triggers":[{"TriggerParts":[{"Operator":"Contains","ValueToCompare":"https://sale-test-ecommerce.queue-it-demo.com/queueit.html","ValuesToCompare":null,"UrlPart":"PageUrl","CookieName":null,"HttpHeaderName":null,"ValidatorType":"UrlValidator","IsNegative":false,"IsIgnoreCase":true},{"Operator":"Contains","ValueToCompare":"ecommerce","ValuesToCompare":null,"UrlPart":null,"CookieName":"QueueITAccepted-SDFrts345E-V3_ecommerce","HttpHeaderName":null,"ValidatorType":"CookieValidator","IsNegative":false,"IsIgnoreCase":true}],"LogicalOperator":"And"}],"QueueDomain":"saletest.queue-it.net","RedirectLogic":null,"ForcedTargetUrl":null},{"IsNormalizationEnabled":false,"QueuePathPrefix":"","InvolvedWaitingRoomIds":null,"VerifyQueueIdEnabled":null,"QueueIdUsageLimit":null,"IsCookieHttpOnly":false,"IsCookieSecure":false,"Name":"aviation","ActionType":"Queue","EventId":"aviation","CookieDomain":"","LayoutName":null,"Culture":null,"ExtendCookieValidity":true,"CookieValidityMinute":1,"Triggers":[{"TriggerParts":[{"Operator":"Contains","ValueToCompare":"sale-test-aviation.queue-it-demo.com","ValuesToCompare":null,"UrlPart":"HostName","CookieName":null,"HttpHeaderName":null,"ValidatorType":"UrlValidator","IsNegative":false,"IsIgnoreCase":true},{"Operator":"ContainsAny","ValueToCompare":"","ValuesToCompare":["akamai","cloudfront","cloudflare"],"UrlPart":"PageUrl","CookieName":null,"HttpHeaderName":null,"ValidatorType":"UrlValidator","IsNegative":true,"IsIgnoreCase":true},{"Operator":"Equals","ValueToCompare":"/bookin.html","ValuesToCompare":null,"UrlPart":"PagePath","CookieName":null,"HttpHeaderName":null,"ValidatorType":"UrlValidator","IsNegative":false,"IsIgnoreCase":true}],"LogicalOperator":"And"}],"QueueDomain":"saletest.queue-it.net","RedirectLogic":"AllowTParameter","ForcedTargetUrl":null},{"IsNormalizationEnabled":false,"QueuePathPrefix":"","InvolvedWaitingRoomIds":null,"VerifyQueueIdEnabled":null,"QueueIdUsageLimit":null,"IsCookieHttpOnly":false,"IsCookieSecure":false,"Name":"Aviation Payment","ActionType":"Queue","EventId":"aviationpayment","CookieDomain":"","LayoutName":null,"Culture":null,"ExtendCookieValidity":true,"CookieValidityMinute":20,"Triggers":[{"TriggerParts":[{"Operator":"Contains","ValueToCompare":"sale-test-aviation","ValuesToCompare":null,"UrlPart":"PageUrl","CookieName":null,"HttpHeaderName":null,"ValidatorType":"UrlValidator","IsNegative":false,"IsIgnoreCase":true},{"Operator":"ContainsAny","ValueToCompare":"","ValuesToCompare":["akamai","cloudfront","cloudflare"],"UrlPart":"PageUrl","CookieName":null,"HttpHeaderName":null,"ValidatorType":"UrlValidator","IsNegative":true,"IsIgnoreCase":true},{"Operator":"Contains","ValueToCompare":"/payment.html","ValuesToCompare":null,"UrlPart":"PageUrl","CookieName":null,"HttpHeaderName":null,"ValidatorType":"UrlValidator","IsNegative":false,"IsIgnoreCase":true}],"LogicalOperator":"And"}],"QueueDomain":"saletest.queue-it.net","RedirectLogic":"AllowTParameter","ForcedTargetUrl":null},{"IsNormalizationEnabled":false,"QueuePathPrefix":"","InvolvedWaitingRoomIds":null,"VerifyQueueIdEnabled":null,"QueueIdUsageLimit":null,"IsCookieHttpOnly":false,"IsCookieSecure":false,"Name":"Ecommerce Queue It","ActionType":"Queue","EventId":"knownuserbuttontest","CookieDomain":"","LayoutName":null,"Culture":null,"ExtendCookieValidity":true,"CookieValidityMinute":20,"Triggers":[{"TriggerParts":[{"Operator":"Contains","ValueToCompare":"sale-test-ecommerce","ValuesToCompare":null,"UrlPart":"PageUrl","CookieName":null,"HttpHeaderName":null,"ValidatorType":"UrlValidator","IsNegative":false,"IsIgnoreCase":true},{"Operator":"ContainsAny","ValueToCompare":"","ValuesToCompare":["akamai","cloudflare"],"UrlPart":"PageUrl","CookieName":null,"HttpHeaderName":null,"ValidatorType":"UrlValidator","IsNegative":true,"IsIgnoreCase":true},{"Operator":"Contains","ValueToCompare":"queueit.html","ValuesToCompare":null,"UrlPart":"PageUrl","CookieName":null,"HttpHeaderName":null,"ValidatorType":"UrlValidator","IsNegative":false,"IsIgnoreCase":true}],"LogicalOperator":"And"}],"QueueDomain":"saletest.queue-it.net","RedirectLogic":"AllowTParameter","ForcedTargetUrl":null},{"IsNormalizationEnabled":false,"QueuePathPrefix":"","InvolvedWaitingRoomIds":null,"VerifyQueueIdEnabled":null,"QueueIdUsageLimit":null,"IsCookieHttpOnly":false,"IsCookieSecure":false,"Name":"Javascript test","ActionType":"Queue","EventId":"javascript","CookieDomain":"","LayoutName":null,"Culture":null,"ExtendCookieValidity":true,"CookieValidityMinute":20,"Triggers":[{"TriggerParts":[{"Operator":"Contains","ValueToCompare":"api/protected","ValuesToCompare":null,"UrlPart":"PageUrl","CookieName":null,"HttpHeaderName":null,"ValidatorType":"UrlValidator","IsNegative":false,"IsIgnoreCase":true}],"LogicalOperator":"And"}],"QueueDomain":"saletest.queue-it.net","RedirectLogic":"EventTargetUrl","ForcedTargetUrl":null},{"IsNormalizationEnabled":false,"QueuePathPrefix":"","InvolvedWaitingRoomIds":null,"VerifyQueueIdEnabled":null,"QueueIdUsageLimit":null,"IsCookieHttpOnly":false,"IsCookieSecure":false,"Name":"e commerce product","ActionType":"Queue","EventId":"ecommerce","CookieDomain":"","LayoutName":null,"Culture":null,"ExtendCookieValidity":true,"CookieValidityMinute":20,"Triggers":[{"TriggerParts":[{"Operator":"Contains","ValueToCompare":"sale-test-ecommerce","ValuesToCompare":null,"UrlPart":"PageUrl","CookieName":null,"HttpHeaderName":null,"ValidatorType":"UrlValidator","IsNegative":false,"IsIgnoreCase":true},{"Operator":"ContainsAny","ValueToCompare":"","ValuesToCompare":["akamai","cloudfront","cloudflare"],"UrlPart":"PageUrl","CookieName":null,"HttpHeaderName":null,"ValidatorType":"UrlValidator","IsNegative":true,"IsIgnoreCase":true},{"Operator":"Contains","ValueToCompare":"ecommerce.html","ValuesToCompare":null,"UrlPart":"PageUrl","CookieName":null,"HttpHeaderName":null,"ValidatorType":"UrlValidator","IsNegative":false,"IsIgnoreCase":true}],"LogicalOperator":"And"}],"QueueDomain":"saletest.queue-it.net","RedirectLogic":"AllowTParameter","ForcedTargetUrl":null},{"IsNormalizationEnabled":false,"QueuePathPrefix":"","InvolvedWaitingRoomIds":null,"VerifyQueueIdEnabled":null,"QueueIdUsageLimit":null,"IsCookieHttpOnly":false,"IsCookieSecure":false,"Name":"e commerce game","ActionType":"Queue","EventId":"gamewaitingroom","CookieDomain":"","LayoutName":null,"Culture":null,"ExtendCookieValidity":true,"CookieValidityMinute":20,"Triggers":[{"TriggerParts":[{"Operator":"Contains","ValueToCompare":"sale-test-ecommerce","ValuesToCompare":null,"UrlPart":"PageUrl","CookieName":null,"HttpHeaderName":null,"ValidatorType":"UrlValidator","IsNegative":false,"IsIgnoreCase":true},{"Operator":"ContainsAny","ValueToCompare":"","ValuesToCompare":["akamai","cloudfront","cloudflare"],"UrlPart":"PageUrl","CookieName":null,"HttpHeaderName":null,"ValidatorType":"UrlValidator","IsNegative":true,"IsIgnoreCase":true},{"Operator":"Contains","ValueToCompare":"shipping.html","ValuesToCompare":null,"UrlPart":"PageUrl","CookieName":null,"HttpHeaderName":null,"ValidatorType":"UrlValidator","IsNegative":false,"IsIgnoreCase":true}],"LogicalOperator":"And"}],"QueueDomain":"saletest.queue-it.net","RedirectLogic":"AllowTParameter","ForcedTargetUrl":null},{"IsNormalizationEnabled":false,"QueuePathPrefix":"","InvolvedWaitingRoomIds":null,"VerifyQueueIdEnabled":null,"QueueIdUsageLimit":null,"IsCookieHttpOnly":false,"IsCookieSecure":false,"Name":"Health Care","ActionType":"Queue","EventId":"healthcare","CookieDomain":"","LayoutName":null,"Culture":null,"ExtendCookieValidity":true,"CookieValidityMinute":20,"Triggers":[{"TriggerParts":[{"Operator":"Contains","ValueToCompare":"sale-test-ecommerce","ValuesToCompare":null,"UrlPart":"PageUrl","CookieName":null,"HttpHeaderName":null,"ValidatorType":"UrlValidator","IsNegative":false,"IsIgnoreCase":true},{"Operator":"ContainsAny","ValueToCompare":"","ValuesToCompare":["akamai","cloudfront","cloudflare"],"UrlPart":"PageUrl","CookieName":null,"HttpHeaderName":null,"ValidatorType":"UrlValidator","IsNegative":true,"IsIgnoreCase":true},{"Operator":"Contains","ValueToCompare":"healthcare.html","ValuesToCompare":null,"UrlPart":"PageUrl","CookieName":null,"HttpHeaderName":null,"ValidatorType":"UrlValidator","IsNegative":false,"IsIgnoreCase":true}],"LogicalOperator":"And"}],"QueueDomain":"saletest.queue-it.net","RedirectLogic":"AllowTParameter","ForcedTargetUrl":null},{"IsNormalizationEnabled":false,"QueuePathPrefix":"","InvolvedWaitingRoomIds":null,"VerifyQueueIdEnabled":null,"QueueIdUsageLimit":null,"IsCookieHttpOnly":false,"IsCookieSecure":false,"Name":"NFT Action and Trigger","ActionType":"Queue","EventId":"nftwaitingroom","CookieDomain":"","LayoutName":null,"Culture":null,"ExtendCookieValidity":true,"CookieValidityMinute":20,"Triggers":[{"TriggerParts":[{"Operator":"Contains","ValueToCompare":"sale-test-ecommerce","ValuesToCompare":null,"UrlPart":"PageUrl","CookieName":null,"HttpHeaderName":null,"ValidatorType":"UrlValidator","IsNegative":false,"IsIgnoreCase":true},{"Operator":"ContainsAny","ValueToCompare":"","ValuesToCompare":["akamai","cloudfront","cloudflare"],"UrlPart":"PageUrl","CookieName":null,"HttpHeaderName":null,"ValidatorType":"UrlValidator","IsNegative":true,"IsIgnoreCase":true},{"Operator":"Contains","ValueToCompare":"nft.html","ValuesToCompare":null,"UrlPart":"PageUrl","CookieName":null,"HttpHeaderName":null,"ValidatorType":"UrlValidator","IsNegative":false,"IsIgnoreCase":true}],"LogicalOperator":"And"}],"QueueDomain":"saletest.queue-it.net","RedirectLogic":"AllowTParameter","ForcedTargetUrl":null},{"IsNormalizationEnabled":false,"QueuePathPrefix":"","InvolvedWaitingRoomIds":null,"VerifyQueueIdEnabled":null,"QueueIdUsageLimit":null,"IsCookieHttpOnly":false,"IsCookieSecure":false,"Name":"ai waiting room trigger","ActionType":"Queue","EventId":"aiwaitingroom","CookieDomain":"","LayoutName":null,"Culture":null,"ExtendCookieValidity":true,"CookieValidityMinute":20,"Triggers":[{"TriggerParts":[{"Operator":"Contains","ValueToCompare":"sale-test-ecommerce","ValuesToCompare":null,"UrlPart":"PageUrl","CookieName":null,"HttpHeaderName":null,"ValidatorType":"UrlValidator","IsNegative":false,"IsIgnoreCase":true},{"Operator":"ContainsAny","ValueToCompare":"","ValuesToCompare":["akamai","cloudfront","cloudflare"],"UrlPart":"PageUrl","CookieName":null,"HttpHeaderName":null,"ValidatorType":"UrlValidator","IsNegative":true,"IsIgnoreCase":true},{"Operator":"Contains","ValueToCompare":"ai.html","ValuesToCompare":null,"UrlPart":"PageUrl","CookieName":null,"HttpHeaderName":null,"ValidatorType":"UrlValidator","IsNegative":false,"IsIgnoreCase":true}],"LogicalOperator":"And"}],"QueueDomain":"saletest.queue-it.net","RedirectLogic":"ForcedTargetUrl","ForcedTargetUrl":"https://www.youtube.com"},{"IsNormalizationEnabled":false,"QueuePathPrefix":"","InvolvedWaitingRoomIds":null,"VerifyQueueIdEnabled":null,"QueueIdUsageLimit":null,"IsCookieHttpOnly":false,"IsCookieSecure":false,"Name":"E commerce checkout","ActionType":"Queue","EventId":"ecommercecheckout","CookieDomain":"","LayoutName":null,"Culture":null,"ExtendCookieValidity":true,"CookieValidityMinute":20,"Triggers":[{"TriggerParts":[{"Operator":"Contains","ValueToCompare":"sale-test-ecommerce","ValuesToCompare":null,"UrlPart":"PageUrl","CookieName":null,"HttpHeaderName":null,"ValidatorType":"UrlValidator","IsNegative":false,"IsIgnoreCase":true},{"Operator":"ContainsAny","ValueToCompare":"","ValuesToCompare":["akamai","cloudfront","cloudflare"],"UrlPart":"PageUrl","CookieName":null,"HttpHeaderName":null,"ValidatorType":"UrlValidator","IsNegative":true,"IsIgnoreCase":true},{"Operator":"Contains","ValueToCompare":"/checkout.html","ValuesToCompare":null,"UrlPart":"PageUrl","CookieName":null,"HttpHeaderName":null,"ValidatorType":"UrlValidator","IsNegative":false,"IsIgnoreCase":true}],"LogicalOperator":"And"}],"QueueDomain":"saletest.queue-it.net","RedirectLogic":"AllowTParameter","ForcedTargetUrl":null},{"IsNormalizationEnabled":false,"QueuePathPrefix":"","InvolvedWaitingRoomIds":null,"VerifyQueueIdEnabled":null,"QueueIdUsageLimit":null,"IsCookieHttpOnly":false,"IsCookieSecure":false,"Name":"Akamai Demo","ActionType":"Queue","EventId":"javascript","CookieDomain":"","LayoutName":null,"Culture":null,"ExtendCookieValidity":true,"CookieValidityMinute":20,"Triggers":[{"TriggerParts":[{"Operator":"Contains","ValueToCompare":"sale-test-demo.queue-it-demo.com/sale.html","ValuesToCompare":null,"UrlPart":"PageUrl","CookieName":null,"HttpHeaderName":null,"ValidatorType":"UrlValidator","IsNegative":false,"IsIgnoreCase":true}],"LogicalOperator":"And"}],"QueueDomain":"saletest.queue-it.net","RedirectLogic":"ForcedTargetUrl","ForcedTargetUrl":"https://sale-test-demo.queue-it-demo.com/sale.html"},{"IsNormalizationEnabled":false,"QueuePathPrefix":"","InvolvedWaitingRoomIds":["javascript","knownuser"],"VerifyQueueIdEnabled":null,"QueueIdUsageLimit":null,"IsCookieHttpOnly":false,"IsCookieSecure":false,"Name":"Copy of Akamai Demo","ActionType":"Cancel","EventId":"javascript","CookieDomain":"","LayoutName":null,"Culture":null,"ExtendCookieValidity":null,"CookieValidityMinute":0,"Triggers":[{"TriggerParts":[{"Operator":"Contains","ValueToCompare":"https://sale-test-demo.queue-it-demo.com/index.html","ValuesToCompare":null,"UrlPart":"PageUrl","CookieName":null,"HttpHeaderName":null,"ValidatorType":"UrlValidator","IsNegative":false,"IsIgnoreCase":true}],"LogicalOperator":"And"}],"QueueDomain":"saletest.queue-it.net","RedirectLogic":null,"ForcedTargetUrl":null},{"IsNormalizationEnabled":false,"QueuePathPrefix":"","InvolvedWaitingRoomIds":null,"VerifyQueueIdEnabled":null,"QueueIdUsageLimit":null,"IsCookieHttpOnly":false,"IsCookieSecure":false,"Name":"akamai","ActionType":"Queue","EventId":"knownuserakamai","CookieDomain":"","LayoutName":null,"Culture":null,"ExtendCookieValidity":true,"CookieValidityMinute":20,"Triggers":[{"TriggerParts":[{"Operator":"Contains","ValueToCompare":"akamai","ValuesToCompare":null,"UrlPart":"PageUrl","CookieName":null,"HttpHeaderName":null,"ValidatorType":"UrlValidator","IsNegative":false,"IsIgnoreCase":true}],"LogicalOperator":"And"}],"QueueDomain":"saletest.queue-it.net","RedirectLogic":"AllowTParameter","ForcedTargetUrl":null},{"IsNormalizationEnabled":false,"QueuePathPrefix":"","InvolvedWaitingRoomIds":null,"VerifyQueueIdEnabled":null,"QueueIdUsageLimit":null,"IsCookieHttpOnly":false,"IsCookieSecure":false,"Name":"knownUserTest","ActionType":"Queue","EventId":"knownuser","CookieDomain":"","LayoutName":null,"Culture":null,"ExtendCookieValidity":true,"CookieValidityMinute":20,"Triggers":[{"TriggerParts":[{"Operator":"Contains","ValueToCompare":"localhost","ValuesToCompare":null,"UrlPart":"HostName","CookieName":null,"HttpHeaderName":null,"ValidatorType":"UrlValidator","IsNegative":false,"IsIgnoreCase":true},{"Operator":"Contains","ValueToCompare":"/checkout","ValuesToCompare":null,"UrlPart":"PagePath","CookieName":null,"HttpHeaderName":null,"ValidatorType":"UrlValidator","IsNegative":true,"IsIgnoreCase":true}],"LogicalOperator":"And"}],"QueueDomain":"saletest.queue-it.net","RedirectLogic":"AllowTParameter","ForcedTargetUrl":null},{"IsNormalizationEnabled":false,"QueuePathPrefix":"","InvolvedWaitingRoomIds":null,"VerifyQueueIdEnabled":null,"QueueIdUsageLimit":null,"IsCookieHttpOnly":false,"IsCookieSecure":false,"Name":"google.com","ActionType":"Queue","EventId":"ecommerce","CookieDomain":"","LayoutName":null,"Culture":null,"ExtendCookieValidity":true,"CookieValidityMinute":20,"Triggers":[{"TriggerParts":[{"Operator":"Contains","ValueToCompare":"google.com","ValuesToCompare":null,"UrlPart":"PageUrl","CookieName":null,"HttpHeaderName":null,"ValidatorType":"UrlValidator","IsNegative":false,"IsIgnoreCase":true}],"LogicalOperator":"And"}],"QueueDomain":"saletest.queue-it.net","RedirectLogic":"AllowTParameter","ForcedTargetUrl":null},{"IsNormalizationEnabled":false,"QueuePathPrefix":"","InvolvedWaitingRoomIds":null,"VerifyQueueIdEnabled":null,"QueueIdUsageLimit":null,"IsCookieHttpOnly":false,"IsCookieSecure":false,"Name":"This is a new example rule","ActionType":"Queue","EventId":"testingidle","CookieDomain":"","LayoutName":null,"Culture":null,"ExtendCookieValidity":true,"CookieValidityMinute":20,"Triggers":[{"TriggerParts":[{"Operator":"Contains","ValueToCompare":"string","ValuesToCompare":null,"UrlPart":"PagePath","CookieName":null,"HttpHeaderName":null,"ValidatorType":"UrlValidator","IsNegative":false,"IsIgnoreCase":true}],"LogicalOperator":"And"}],"QueueDomain":"saletest.queue-it.net","RedirectLogic":"AllowTParameter","ForcedTargetUrl":null},{"IsNormalizationEnabled":false,"QueuePathPrefix":"","InvolvedWaitingRoomIds":null,"VerifyQueueIdEnabled":null,"QueueIdUsageLimit":null,"IsCookieHttpOnly":false,"IsCookieSecure":false,"Name":"GentleMonster Event-renewal-test.gentlemonster.com-/kr","ActionType":"Queue","EventId":"testingidle","CookieDomain":"","LayoutName":null,"Culture":null,"ExtendCookieValidity":true,"CookieValidityMinute":20,"Triggers":[{"TriggerParts":[{"Operator":"Contains","ValueToCompare":"renewal-test.gentlemonster.com","ValuesToCompare":null,"UrlPart":"HostName","CookieName":null,"HttpHeaderName":null,"ValidatorType":"UrlValidator","IsNegative":false,"IsIgnoreCase":true},{"Operator":"Contains","ValueToCompare":"/kr","ValuesToCompare":null,"UrlPart":"PagePath","CookieName":null,"HttpHeaderName":null,"ValidatorType":"UrlValidator","IsNegative":false,"IsIgnoreCase":true},{"Operator":"ContainsAny","ValueToCompare":"","ValuesToCompare":["0P0M4JBR5F0HM/bonit9","0P0M4JBR5F0HM/bonit10","0P0M4JBR5F0HM/bonit11","0P0M4JBR5F0HM/bonit12","0P0M4JBR5F0HM/bonit13","0P0M4JBR5F0HM/bonit14","0P0M4JBR5F0HM/bonit15","0P0M4JBR5F0HM/bonit16","0P0M4JBR5F0HM/bonit17","0P0M4JBR5F0HM/bonit18","0P0M4JBR5F0HM/bonit19","0P0M4JBR5F0HM/bonit20","0P0M4JBR5F0HM/bonit21","0P0M4JBR5F0HM/bonit22","0P0M4JBR5F0HM/bonit23","0P0M4JBR5F0HM/bonit24","0P0M4JBR5F0HM/bonit25","0P0M4JBR5F0HM/bonit26","0P0M4JBR5F0HM/bonit27","0P0M4JBR5F0HM/bonit28","0P0M4JBR5F0HM/bonit29","0P0M4JBR5F0HM/bonit30","0P0M4JBR5F0HM/bonit31","0P0M4JBR5F0HM/bonit32","0P0M4JBR5F0HM/bonit33","0P0M4JBR5F0HM/bonit34","0P0M4JBR5F0HM/bonit35","0P0M4JBR5F0HM/bonit36","0P0M4JBR5F0HM/bonit37","0P0M4JBR5F0HM/bonit38"],"UrlPart":"PagePath","CookieName":null,"HttpHeaderName":null,"ValidatorType":"UrlValidator","IsNegative":false,"IsIgnoreCase":true}],"LogicalOperator":"And"}],"QueueDomain":"saletest.queue-it.net","RedirectLogic":"AllowTParameter","ForcedTargetUrl":null},{"IsNormalizationEnabled":false,"QueuePathPrefix":"","InvolvedWaitingRoomIds":null,"VerifyQueueIdEnabled":null,"QueueIdUsageLimit":null,"IsCookieHttpOnly":false,"IsCookieSecure":false,"Name":"GentleMonster Event-renewal-test.gentlemonster.com-/jp","ActionType":"Queue","EventId":"testingidle","CookieDomain":"","LayoutName":null,"Culture":null,"ExtendCookieValidity":true,"CookieValidityMinute":20,"Triggers":[{"TriggerParts":[{"Operator":"Contains","ValueToCompare":"renewal-test.gentlemonster.com","ValuesToCompare":null,"UrlPart":"HostName","CookieName":null,"HttpHeaderName":null,"ValidatorType":"UrlValidator","IsNegative":false,"IsIgnoreCase":true},{"Operator":"Contains","ValueToCompare":"/jp","ValuesToCompare":null,"UrlPart":"PagePath","CookieName":null,"HttpHeaderName":null,"ValidatorType":"UrlValidator","IsNegative":false,"IsIgnoreCase":true},{"Operator":"ContainsAny","ValueToCompare":"","ValuesToCompare":["0P0M4JBR5F0HM/bonit39","0P0M4JBR5F0HM/bonit40","0P0M4JBR5F0HM/bonit41","0P0M4JBR5F0HM/bonit42","0P0M4JBR5F0HM/bonit43","0P0M4JBR5F0HM/bonit44","0P0M4JBR5F0HM/bonit45","0P0M4JBR5F0HM/bonit46","0P0M4JBR5F0HM/bonit47"],"UrlPart":"PagePath","CookieName":null,"HttpHeaderName":null,"ValidatorType":"UrlValidator","IsNegative":false,"IsIgnoreCase":true}],"LogicalOperator":"And"}],"QueueDomain":"saletest.queue-it.net","RedirectLogic":"AllowTParameter","ForcedTargetUrl":null},{"IsNormalizationEnabled":false,"QueuePathPrefix":"","InvolvedWaitingRoomIds":null,"VerifyQueueIdEnabled":null,"QueueIdUsageLimit":null,"IsCookieHttpOnly":false,"IsCookieSecure":false,"Name":"Ignore Good Bots","ActionType":"Queue","EventId":"aiwaitingroom","CookieDomain":"","LayoutName":null,"Culture":null,"ExtendCookieValidity":true,"CookieValidityMinute":20,"Triggers":[{"TriggerParts":[{"Operator":"ContainsAny","ValueToCompare":"","ValuesToCompare":["adsbot-google","AdsBot-Google-Mobile","AdsBot-Google-Mobile-Apps","AhrefsBot","APIs-Google","Applebot","Baiduspider","bingbot","BingPreview","DotBot","DuckDuckBot","DuplexWeb-Google","facebookexternalhit","Facebot","FeedFetcher-Google","Google Favicon","Google-Adwords-Instant","Google-Read-Aloud","Google-Site-Verification","googlebot","Googlebot-image","Googlebot-News","Googlebot-Video","Image size by Siteimprove.com","LinkCheck by Siteimprove.com","Mail.RU_Bot","Mappy","Mediapartners-Google","MJ12bot","nlnbot","Pinterestbot","Prerender","SemrushBot","SiteCheck-sitecrawl by Siteimprove.com","Slackbot-LinkExpanding","UptimeRobot","Yahoo! Slurp","Yahoo!-AdCrawler","YandexBot"],"UrlPart":null,"CookieName":null,"HttpHeaderName":null,"ValidatorType":"UserAgentValidator","IsNegative":false,"IsIgnoreCase":true},{"Operator":"Contains","ValueToCompare":"/checkout","ValuesToCompare":null,"UrlPart":"PageUrl","CookieName":null,"HttpHeaderName":null,"ValidatorType":"UrlValidator","IsNegative":false,"IsIgnoreCase":true}],"LogicalOperator":"And"}],"QueueDomain":"saletest.queue-it.net","RedirectLogic":"AllowTParameter","ForcedTargetUrl":null},{"IsNormalizationEnabled":false,"QueuePathPrefix":"","InvolvedWaitingRoomIds":null,"VerifyQueueIdEnabled":null,"QueueIdUsageLimit":null,"IsCookieHttpOnly":false,"IsCookieSecure":false,"Name":"lg demo","ActionType":"Queue","EventId":"testajax","CookieDomain":"","LayoutName":null,"Culture":null,"ExtendCookieValidity":true,"CookieValidityMinute":20,"Triggers":[{"TriggerParts":[{"Operator":"Contains","ValueToCompare":"lgdemo.vercel.app","ValuesToCompare":null,"UrlPart":"HostName","CookieName":null,"HttpHeaderName":null,"ValidatorType":"UrlValidator","IsNegative":false,"IsIgnoreCase":true},{"Operator":"Contains","ValueToCompare":"lgdemo.vercel.app/tv","ValuesToCompare":null,"UrlPart":null,"CookieName":null,"HttpHeaderName":"Referer","ValidatorType":"HttpHeaderValidator","IsNegative":false,"IsIgnoreCase":true},{"Operator":"Contains","ValueToCompare":"/api/product","ValuesToCompare":null,"UrlPart":"PagePath","CookieName":null,"HttpHeaderName":null,"ValidatorType":"UrlValidator","IsNegative":false,"IsIgnoreCase":true}],"LogicalOperator":"And"}],"QueueDomain":"saletest.queue-it.net","RedirectLogic":"ForcedTargetUrl","ForcedTargetUrl":"https://lgdemo.vercel.app/tv"}],"CustomerId":"saletest","AccountId":"queueit-sale","Version":174,"PublishDate":"2026-04-17T00:19:59.5217728Z"}